{
  "configurations": [
    {
      "name": "Win-MSVC-x86-Debug",
      "generator": "Ninja",
      "configurationType": "Debug",
      "inheritEnvironments": [ "msvc_x86" ],
      "buildRoot": "${env.USERPROFILE}\\CMakeBuilds\\${workspaceHash}\\build\\${name}",
      "installRoot": "${env.USERPROFILE}\\CMakeBuilds\\${workspaceHash}\\install\\${name}",
      "cmakeCommandArgs": "",
      "buildCommandArgs": "",
      "variables": [
        {
          "name": "CMAKE_TOOLCHAIN_FILE",
          "value": "${env.VCPKG_ROOT}/scripts/buildsystems/vcpkg.cmake",
          "type": "STRING"
        },
        {
          "name": "BUILD_TESTS",
          "value": "True",
          "type": "BOOL"
        },
        {
          "name": "BUILD_BENCHMARKS",
          "value": "True",
          "type": "BOOL"
        },
        {
          "name": "BUILD_RAPIDJSON_ARCHIVE",
          "value": "True",
          "type": "BOOL"
        },
        {
          "name": "BUILD_PUGIXML_ARCHIVE",
          "value": "True",
          "type": "BOOL"
        },
        {
          "name": "BUILD_RAPIDYAML_ARCHIVE",
          "value": "True",
          "type": "BOOL"
        },
        {
          "name": "BUILD_CSV_ARCHIVE",
          "value": "True",
          "type": "BOOL"
        },
        {
          "name": "BUILD_MSGPACK_ARCHIVE",
          "value": "True",
          "type": "BOOL"
        }
      ]
    },
    {
      "name": "Win-MSVC-x86-Release",
      "generator": "Ninja",
      "configurationType": "Release",
      "inheritEnvironments": [ "msvc_x86" ],
      "buildRoot": "${env.USERPROFILE}\\CMakeBuilds\\${workspaceHash}\\build\\${name}",
      "installRoot": "${env.USERPROFILE}\\CMakeBuilds\\${workspaceHash}\\install\\${name}",
      "cmakeCommandArgs": "",
      "buildCommandArgs": "",
      "variables": [
        {
          "name": "CMAKE_TOOLCHAIN_FILE",
          "value": "${env.VCPKG_ROOT}/scripts/buildsystems/vcpkg.cmake",
          "type": "STRING"
        },
        {
          "name": "BUILD_TESTS",
          "value": "True",
          "type": "BOOL"
        },
        {
          "name": "BUILD_BENCHMARKS",
          "value": "True",
          "type": "BOOL"
        },
        {
          "name": "BUILD_SAMPLES",
          "value": "True",
          "type": "BOOL"
        },
        {
          "name": "BUILD_RAPIDJSON_ARCHIVE",
          "value": "True",
          "type": "BOOL"
        },
        {
          "name": "BUILD_PUGIXML_ARCHIVE",
          "value": "True",
          "type": "BOOL"
        },
        {
          "name": "BUILD_RAPIDYAML_ARCHIVE",
          "value": "True",
          "type": "BOOL"
        },
        {
          "name": "BUILD_CSV_ARCHIVE",
          "value": "True",
          "type": "BOOL"
        },
        {
          "name": "BUILD_MSGPACK_ARCHIVE",
          "value": "True",
          "type": "BOOL"
        }
      ]
    },
    {
      "name": "Win-MSVC-x64-Debug",
      "generator": "Ninja",
      "configurationType": "Debug",
      "inheritEnvironments": [ "msvc_x64_x64" ],
      "buildRoot": "${env.USERPROFILE}\\CMakeBuilds\\${workspaceHash}\\build\\${name}",
      "installRoot": "${env.USERPROFILE}\\CMakeBuilds\\${workspaceHash}\\install\\${name}",
      "cmakeCommandArgs": "",
      "buildCommandArgs": "",
      "variables": [
        {
          "name": "CMAKE_TOOLCHAIN_FILE",
          "value": "${env.VCPKG_ROOT}/scripts/buildsystems/vcpkg.cmake",
          "type": "STRING"
        },
        {
          "name": "BUILD_TESTS",
          "value": "True",
          "type": "BOOL"
        },
        {
          "name": "BUILD_BENCHMARKS",
          "value": "True",
          "type": "BOOL"
        },
        {
          "name": "BUILD_SAMPLES",
          "value": "True",
          "type": "BOOL"
        },
        {
          "name": "BUILD_RAPIDJSON_ARCHIVE",
          "value": "True",
          "type": "BOOL"
        },
        {
          "name": "BUILD_PUGIXML_ARCHIVE",
          "value": "True",
          "type": "BOOL"
        },
        {
          "name": "BUILD_RAPIDYAML_ARCHIVE",
          "value": "True",
          "type": "BOOL"
        },
        {
          "name": "BUILD_CSV_ARCHIVE",
          "value": "True",
          "type": "BOOL"
        },
        {
          "name": "BUILD_MSGPACK_ARCHIVE",
          "value": "True",
          "type": "BOOL"
        }
      ]
    },
    {
      "name": "Win-MSVC-x64-Debug+Analysis",
      "generator": "Ninja",
      "configurationType": "Debug",
      "inheritEnvironments": [ "msvc_x64_x64" ],
      "buildRoot": "${env.USERPROFILE}\\CMakeBuilds\\${workspaceHash}\\build\\${name}",
      "installRoot": "${env.USERPROFILE}\\CMakeBuilds\\${workspaceHash}\\install\\${name}",
      "cmakeCommandArgs": "",
      "buildCommandArgs": "",
      "variables": [
        {
          "name": "CMAKE_TOOLCHAIN_FILE",
          "value": "${env.VCPKG_ROOT}/scripts/buildsystems/vcpkg.cmake",
          "type": "STRING"
        },
        {
          "name": "STATIC_ANALYSIS_CLANG_TIDY",
          "value": "True",
          "type": "BOOL"
        },
        {
          "name": "BUILD_TESTS",
          "value": "True",
          "type": "BOOL"
        },
        {
          "name": "BUILD_BENCHMARKS",
          "value": "True",
          "type": "BOOL"
        },
        {
          "name": "BUILD_SAMPLES",
          "value": "True",
          "type": "BOOL"
        },
        {
          "name": "BUILD_RAPIDJSON_ARCHIVE",
          "value": "True",
          "type": "BOOL"
        },
        {
          "name": "BUILD_PUGIXML_ARCHIVE",
          "value": "True",
          "type": "BOOL"
        },
        {
          "name": "BUILD_RAPIDYAML_ARCHIVE",
          "value": "False",
          "type": "BOOL"
        },
        {
          "name": "BUILD_CSV_ARCHIVE",
          "value": "True",
          "type": "BOOL"
        },
        {
          "name": "BUILD_MSGPACK_ARCHIVE",
          "value": "True",
          "type": "BOOL"
        }
      ]
    },
    {
      "name": "Win-MSVC-x64-Release",
      "generator": "Ninja",
      "configurationType": "Release",
      "inheritEnvironments": [ "msvc_x64_x64" ],
      "buildRoot": "${env.USERPROFILE}\\CMakeBuilds\\${workspaceHash}\\build\\${name}",
      "installRoot": "${env.USERPROFILE}\\CMakeBuilds\\${workspaceHash}\\install\\${name}",
      "cmakeCommandArgs": "",
      "buildCommandArgs": "",
      "variables": [
        {
          "name": "CMAKE_TOOLCHAIN_FILE",
          "value": "${env.VCPKG_ROOT}/scripts/buildsystems/vcpkg.cmake",
          "type": "STRING"
        },
        {
          "name": "BUILD_TESTS",
          "value": "True",
          "type": "BOOL"
        },
        {
          "name": "BUILD_BENCHMARKS",
          "value": "True",
          "type": "BOOL"
        },
        {
          "name": "BUILD_SAMPLES",
          "value": "True",
          "type": "BOOL"
        },
        {
          "name": "BUILD_RAPIDJSON_ARCHIVE",
          "value": "True",
          "type": "BOOL"
        },
        {
          "name": "BUILD_PUGIXML_ARCHIVE",
          "value": "True",
          "type": "BOOL"
        },
        {
          "name": "BUILD_RAPIDYAML_ARCHIVE",
          "value": "True",
          "type": "BOOL"
        },
        {
          "name": "BUILD_CSV_ARCHIVE",
          "value": "True",
          "type": "BOOL"
        },
        {
          "name": "BUILD_MSGPACK_ARCHIVE",
          "value": "True",
          "type": "BOOL"
        }
      ]
    },
    {
      "name": "Win-MSVC-x64-CXX20-Debug",
      "generator": "Ninja",
      "configurationType": "Debug",
      "inheritEnvironments": [ "msvc_x64_x64" ],
      "buildRoot": "${env.USERPROFILE}\\CMakeBuilds\\${workspaceHash}\\build\\${name}",
      "installRoot": "${env.USERPROFILE}\\CMakeBuilds\\${workspaceHash}\\install\\${name}",
      "cmakeCommandArgs": "-DCMAKE_CXX_STANDARD=20",
      "buildCommandArgs": "",
      "variables": [
        {
          "name": "CMAKE_TOOLCHAIN_FILE",
          "value": "${env.VCPKG_ROOT}/scripts/buildsystems/vcpkg.cmake",
          "type": "STRING"
        },
        {
          "name": "BUILD_TESTS",
          "value": "True",
          "type": "BOOL"
        },
        {
          "name": "BUILD_BENCHMARKS",
          "value": "True",
          "type": "BOOL"
        },
        {
          "name": "BUILD_SAMPLES",
          "value": "True",
          "type": "BOOL"
        },
        {
          "name": "BUILD_RAPIDJSON_ARCHIVE",
          "value": "True",
          "type": "BOOL"
        },
        {
          "name": "BUILD_PUGIXML_ARCHIVE",
          "value": "True",
          "type": "BOOL"
        },
        {
          "name": "BUILD_RAPIDYAML_ARCHIVE",
          "value": "True",
          "type": "BOOL"
        },
        {
          "name": "BUILD_CSV_ARCHIVE",
          "value": "True",
          "type": "BOOL"
        },
        {
          "name": "BUILD_MSGPACK_ARCHIVE",
          "value": "True",
          "type": "BOOL"
        }
      ]
    },
    {
      "name": "Win-MSVC-x64-CXX20-Release",
      "generator": "Ninja",
      "configurationType": "Release",
      "inheritEnvironments": [ "msvc_x64_x64" ],
      "buildRoot": "${env.USERPROFILE}\\CMakeBuilds\\${workspaceHash}\\build\\${name}",
      "installRoot": "${env.USERPROFILE}\\CMakeBuilds\\${workspaceHash}\\install\\${name}",
      "cmakeCommandArgs": "-DCMAKE_CXX_STANDARD=20",
      "buildCommandArgs": "",
      "variables": [
        {
          "name": "CMAKE_TOOLCHAIN_FILE",
          "value": "${env.VCPKG_ROOT}/scripts/buildsystems/vcpkg.cmake",
          "type": "STRING"
        },
        {
          "name": "BUILD_TESTS",
          "value": "True",
          "type": "BOOL"
        },
        {
          "name": "BUILD_BENCHMARKS",
          "value": "True",
          "type": "BOOL"
        },
        {
          "name": "BUILD_SAMPLES",
          "value": "True",
          "type": "BOOL"
        },
        {
          "name": "BUILD_RAPIDJSON_ARCHIVE",
          "value": "True",
          "type": "BOOL"
        },
        {
          "name": "BUILD_PUGIXML_ARCHIVE",
          "value": "True",
          "type": "BOOL"
        },
        {
          "name": "BUILD_RAPIDYAML_ARCHIVE",
          "value": "True",
          "type": "BOOL"
        },
        {
          "name": "BUILD_CSV_ARCHIVE",
          "value": "True",
          "type": "BOOL"
        },
        {
          "name": "BUILD_MSGPACK_ARCHIVE",
          "value": "True",
          "type": "BOOL"
        }
      ]
    },
    {
      "name": "Linux-GCC8-Debug",
      "generator": "Ninja",
      "configurationType": "Debug",
      "cmakeExecutable": "cmake",
      "remoteCopySourcesExclusionList": [ ".vs", ".git", "out", "bin" ],
      "cmakeCommandArgs": "-DCMAKE_C_COMPILER=gcc-8 -DCMAKE_CXX_COMPILER=g++-8",
      "buildCommandArgs": "",
      "ctestCommandArgs": "",
      "inheritEnvironments": [ "linux_x64" ],
      "remoteMachineName": "${defaultRemoteMachineName}",
      "remoteCMakeListsRoot": "$HOME/.vs/${projectDirName}/${workspaceHash}/src",
      "remoteBuildRoot": "$HOME/.vs/${projectDirName}/${workspaceHash}/out/build/${name}",
      "remoteInstallRoot": "$HOME/.vs/${projectDirName}/${workspaceHash}/out/install/${name}",
      "remoteCopySources": true,
      "rsyncCommandArgs": "-t --delete",
      "remoteCopyBuildOutput": false,
      "remoteCopySourcesMethod": "rsync",
      "variables": [
        {
          "name": "BUILD_SAMPLES",
          "value": "True",
          "type": "BOOL"
        },
        {
          "name": "BUILD_TESTS",
          "value": "True",
          "type": "BOOL"
        },
        {
          "name": "BUILD_BENCHMARKS",
          "value": "True",
          "type": "BOOL"
        },
        {
          "name": "BUILD_RAPIDJSON_ARCHIVE",
          "value": "True",
          "type": "BOOL"
        },
        {
          "name": "BUILD_PUGIXML_ARCHIVE",
          "value": "True",
          "type": "BOOL"
        },
        {
          "name": "BUILD_RAPIDYAML_ARCHIVE",
          "value": "True",
          "type": "BOOL"
        },
        {
          "name": "BUILD_CSV_ARCHIVE",
          "value": "True",
          "type": "BOOL"
        },
        {
          "name": "BUILD_MSGPACK_ARCHIVE",
          "value": "True",
          "type": "BOOL"
        }
      ]
    },
    {
      "name": "Linux-GCC8-Release",
      "generator": "Ninja",
      "configurationType": "RelWithDebInfo",
      "cmakeExecutable": "cmake",
      "remoteCopySourcesExclusionList": [ ".vs", ".git", "out", "bin" ],
      "cmakeCommandArgs": "-DCMAKE_C_COMPILER=gcc-8 -DCMAKE_CXX_COMPILER=g++-8",
      "buildCommandArgs": "",
      "ctestCommandArgs": "",
      "inheritEnvironments": [ "linux_x64" ],
      "remoteMachineName": "${defaultRemoteMachineName}",
      "remoteCMakeListsRoot": "$HOME/.vs/${projectDirName}/${workspaceHash}/src",
      "remoteBuildRoot": "$HOME/.vs/${projectDirName}/${workspaceHash}/out/build/${name}",
      "remoteInstallRoot": "$HOME/.vs/${projectDirName}/${workspaceHash}/out/install/${name}",
      "remoteCopySources": true,
      "rsyncCommandArgs": "-t --delete",
      "remoteCopyBuildOutput": false,
      "remoteCopySourcesMethod": "rsync",
      "variables": [
        {
          "name": "BUILD_SAMPLES",
          "value": "True",
          "type": "BOOL"
        },
        {
          "name": "BUILD_TESTS",
          "value": "True",
          "type": "BOOL"
        },
        {
          "name": "BUILD_BENCHMARKS",
          "value": "True",
          "type": "BOOL"
        },
        {
          "name": "BUILD_RAPIDJSON_ARCHIVE",
          "value": "True",
          "type": "BOOL"
        },
        {
          "name": "BUILD_PUGIXML_ARCHIVE",
          "value": "True",
          "type": "BOOL"
        },
        {
          "name": "BUILD_RAPIDYAML_ARCHIVE",
          "value": "True",
          "type": "BOOL"
        },
        {
          "name": "BUILD_CSV_ARCHIVE",
          "value": "True",
          "type": "BOOL"
        },
        {
          "name": "BUILD_MSGPACK_ARCHIVE",
          "value": "True",
          "type": "BOOL"
        }
      ]
    },
    {
      "name": "Linux-GCC12-CXX20-Debug",
      "generator": "Ninja",
      "configurationType": "Debug",
      "cmakeExecutable": "cmake",
      "remoteCopySourcesExclusionList": [ ".vs", ".git", "out", "bin" ],
      "cmakeCommandArgs": "-DCMAKE_C_COMPILER=gcc-12 -DCMAKE_CXX_COMPILER=g++-12 -DCMAKE_CXX_STANDARD=20",
      "buildCommandArgs": "",
      "ctestCommandArgs": "",
      "inheritEnvironments": [ "linux_x64" ],
      "remoteMachineName": "${defaultRemoteMachineName}",
      "remoteCMakeListsRoot": "$HOME/.vs/${projectDirName}/${workspaceHash}/src",
      "remoteBuildRoot": "$HOME/.vs/${projectDirName}/${workspaceHash}/out/build/${name}",
      "remoteInstallRoot": "$HOME/.vs/${projectDirName}/${workspaceHash}/out/install/${name}",
      "remoteCopySources": true,
      "rsyncCommandArgs": "-t --delete",
      "remoteCopyBuildOutput": false,
      "remoteCopySourcesMethod": "rsync",
      "variables": [
        {
          "name": "BUILD_SAMPLES",
          "value": "True",
          "type": "BOOL"
        },
        {
          "name": "BUILD_TESTS",
          "value": "True",
          "type": "BOOL"
        },
        {
          "name": "BUILD_BENCHMARKS",
          "value": "True",
          "type": "BOOL"
        },
        {
          "name": "BUILD_RAPIDJSON_ARCHIVE",
          "value": "True",
          "type": "BOOL"
        },
        {
          "name": "BUILD_PUGIXML_ARCHIVE",
          "value": "True",
          "type": "BOOL"
        },
        {
          "name": "BUILD_RAPIDYAML_ARCHIVE",
          "value": "True",
          "type": "BOOL"
        },
        {
          "name": "BUILD_CSV_ARCHIVE",
          "value": "True",
          "type": "BOOL"
        },
        {
          "name": "BUILD_MSGPACK_ARCHIVE",
          "value": "True",
          "type": "BOOL"
        }
      ]
    },
    {
      "name": "Linux-GCC12-CXX20-Release",
      "generator": "Ninja",
      "configurationType": "RelWithDebInfo",
      "cmakeExecutable": "cmake",
      "remoteCopySourcesExclusionList": [ ".vs", ".git", "out", "bin" ],
      "cmakeCommandArgs": "-DCMAKE_C_COMPILER=gcc-12 -DCMAKE_CXX_COMPILER=g++-12 -DCMAKE_CXX_STANDARD=20",
      "buildCommandArgs": "",
      "ctestCommandArgs": "",
      "inheritEnvironments": [ "linux_x64" ],
      "remoteMachineName": "${defaultRemoteMachineName}",
      "remoteCMakeListsRoot": "$HOME/.vs/${projectDirName}/${workspaceHash}/src",
      "remoteBuildRoot": "$HOME/.vs/${projectDirName}/${workspaceHash}/out/build/${name}",
      "remoteInstallRoot": "$HOME/.vs/${projectDirName}/${workspaceHash}/out/install/${name}",
      "remoteCopySources": true,
      "rsyncCommandArgs": "-t --delete",
      "remoteCopyBuildOutput": false,
      "remoteCopySourcesMethod": "rsync",
      "variables": [
        {
          "name": "BUILD_SAMPLES",
          "value": "True",
          "type": "BOOL"
        },
        {
          "name": "BUILD_TESTS",
          "value": "True",
          "type": "BOOL"
        },
        {
          "name": "BUILD_BENCHMARKS",
          "value": "True",
          "type": "BOOL"
        },
        {
          "name": "BUILD_RAPIDJSON_ARCHIVE",
          "value": "True",
          "type": "BOOL"
        },
        {
          "name": "BUILD_PUGIXML_ARCHIVE",
          "value": "True",
          "type": "BOOL"
        },
        {
          "name": "BUILD_RAPIDYAML_ARCHIVE",
          "value": "True",
          "type": "BOOL"
        },
        {
          "name": "BUILD_CSV_ARCHIVE",
          "value": "True",
          "type": "BOOL"
        },
        {
          "name": "BUILD_MSGPACK_ARCHIVE",
          "value": "True",
          "type": "BOOL"
        }
      ]
    },
    {
      "name": "Linux-Clang8-Debug",
      "generator": "Ninja",
      "configurationType": "Debug",
      "cmakeExecutable": "cmake",
      "remoteCopySourcesExclusionList": [ ".vs", ".git", "out", "bin" ],
      "cmakeCommandArgs": "-DCMAKE_C_COMPILER=clang-8 -DCMAKE_CXX_COMPILER=clang++-8",
      "buildCommandArgs": "",
      "ctestCommandArgs": "",
      "inheritEnvironments": [ "linux_x64" ],
      "remoteMachineName": "${defaultRemoteMachineName}",
      "remoteCMakeListsRoot": "$HOME/.vs/${projectDirName}/${workspaceHash}/src",
      "remoteBuildRoot": "$HOME/.vs/${projectDirName}/${workspaceHash}/out/build/${name}",
      "remoteInstallRoot": "$HOME/.vs/${projectDirName}/${workspaceHash}/out/install/${name}",
      "remoteCopySources": true,
      "rsyncCommandArgs": "-t --delete",
      "remoteCopyBuildOutput": false,
      "remoteCopySourcesMethod": "rsync",
      "variables": [
        {
          "name": "BUILD_SAMPLES",
          "value": "True",
          "type": "BOOL"
        },
        {
          "name": "BUILD_TESTS",
          "value": "True",
          "type": "BOOL"
        },
        {
          "name": "BUILD_BENCHMARKS",
          "value": "True",
          "type": "BOOL"
        },
        {
          "name": "BUILD_RAPIDJSON_ARCHIVE",
          "value": "True",
          "type": "BOOL"
        },
        {
          "name": "BUILD_PUGIXML_ARCHIVE",
          "value": "True",
          "type": "BOOL"
        },
        {
          "name": "BUILD_RAPIDYAML_ARCHIVE",
          "value": "True",
          "type": "BOOL"
        },
        {
          "name": "BUILD_CSV_ARCHIVE",
          "value": "True",
          "type": "BOOL"
        },
        {
          "name": "BUILD_MSGPACK_ARCHIVE",
          "value": "True",
          "type": "BOOL"
        }
      ]
    },
    {
      "name": "Linux-Clang8-Release",
      "generator": "Ninja",
      "configurationType": "RelWithDebInfo",
      "cmakeExecutable": "cmake",
      "remoteCopySourcesExclusionList": [ ".vs", ".git", "out", "bin" ],
      "cmakeCommandArgs": "-DCMAKE_C_COMPILER=clang-8 -DCMAKE_CXX_COMPILER=clang++-8",
      "buildCommandArgs": "",
      "ctestCommandArgs": "",
      "inheritEnvironments": [ "linux_x64" ],
      "remoteMachineName": "${defaultRemoteMachineName}",
      "remoteCMakeListsRoot": "$HOME/.vs/${projectDirName}/${workspaceHash}/src",
      "remoteBuildRoot": "$HOME/.vs/${projectDirName}/${workspaceHash}/out/build/${name}",
      "remoteInstallRoot": "$HOME/.vs/${projectDirName}/${workspaceHash}/out/install/${name}",
      "remoteCopySources": true,
      "rsyncCommandArgs": "-t --delete",
      "remoteCopyBuildOutput": false,
      "remoteCopySourcesMethod": "rsync",
      "variables": [
        {
          "name": "BUILD_SAMPLES",
          "value": "True",
          "type": "BOOL"
        },
        {
          "name": "BUILD_TESTS",
          "value": "True",
          "type": "BOOL"
        },
        {
          "name": "BUILD_BENCHMARKS",
          "value": "True",
          "type": "BOOL"
        },
        {
          "name": "BUILD_RAPIDJSON_ARCHIVE",
          "value": "True",
          "type": "BOOL"
        },
        {
          "name": "BUILD_PUGIXML_ARCHIVE",
          "value": "True",
          "type": "BOOL"
        },
        {
          "name": "BUILD_RAPIDYAML_ARCHIVE",
          "value": "True",
          "type": "BOOL"
        },
        {
          "name": "BUILD_CSV_ARCHIVE",
          "value": "True",
          "type": "BOOL"
        },
        {
          "name": "BUILD_MSGPACK_ARCHIVE",
          "value": "True",
          "type": "BOOL"
        }
      ]
    },
    {
      "name": "Linux-Clang14-CXX20-Debug",
      "generator": "Ninja",
      "configurationType": "Debug",
      "cmakeExecutable": "cmake",
      "remoteCopySourcesExclusionList": [ ".vs", ".git", "out", "bin" ],
      "cmakeCommandArgs": "-DCMAKE_C_COMPILER=clang-14 -DCMAKE_CXX_COMPILER=clang++-14 -DCMAKE_CXX_STANDARD=20",
      "buildCommandArgs": "",
      "ctestCommandArgs": "",
      "inheritEnvironments": [ "linux_x64" ],
      "remoteMachineName": "${defaultRemoteMachineName}",
      "remoteCMakeListsRoot": "$HOME/.vs/${projectDirName}/${workspaceHash}/src",
      "remoteBuildRoot": "$HOME/.vs/${projectDirName}/${workspaceHash}/out/build/${name}",
      "remoteInstallRoot": "$HOME/.vs/${projectDirName}/${workspaceHash}/out/install/${name}",
      "remoteCopySources": true,
      "rsyncCommandArgs": "-t --delete",
      "remoteCopyBuildOutput": false,
      "remoteCopySourcesMethod": "rsync",
      "variables": [
        {
          "name": "BUILD_SAMPLES",
          "value": "True",
          "type": "BOOL"
        },
        {
          "name": "BUILD_TESTS",
          "value": "True",
          "type": "BOOL"
        },
        {
          "name": "BUILD_BENCHMARKS",
          "value": "True",
          "type": "BOOL"
        },
        {
          "name": "BUILD_RAPIDJSON_ARCHIVE",
          "value": "True",
          "type": "BOOL"
        },
        {
          "name": "BUILD_PUGIXML_ARCHIVE",
          "value": "True",
          "type": "BOOL"
        },
        {
          "name": "BUILD_RAPIDYAML_ARCHIVE",
          "value": "True",
          "type": "BOOL"
        },
        {
          "name": "BUILD_CSV_ARCHIVE",
          "value": "True",
          "type": "BOOL"
        },
        {
          "name": "BUILD_MSGPACK_ARCHIVE",
          "value": "True",
          "type": "BOOL"
        }
      ]
    },
    {
      "name": "Linux-Clang14-CXX20-Release",
      "generator": "Ninja",
      "configurationType": "RelWithDebInfo",
      "cmakeExecutable": "cmake",
      "remoteCopySourcesExclusionList": [ ".vs", ".git", "out", "bin" ],
      "cmakeCommandArgs": "-DCMAKE_C_COMPILER=clang-14 -DCMAKE_CXX_COMPILER=clang++-14 -DCMAKE_CXX_STANDARD=20",
      "buildCommandArgs": "",
      "ctestCommandArgs": "",
      "inheritEnvironments": [ "linux_x64" ],
      "remoteMachineName": "${defaultRemoteMachineName}",
      "remoteCMakeListsRoot": "$HOME/.vs/${projectDirName}/${workspaceHash}/src",
      "remoteBuildRoot": "$HOME/.vs/${projectDirName}/${workspaceHash}/out/build/${name}",
      "remoteInstallRoot": "$HOME/.vs/${projectDirName}/${workspaceHash}/out/install/${name}",
      "remoteCopySources": true,
      "rsyncCommandArgs": "-t --delete",
      "remoteCopyBuildOutput": false,
      "remoteCopySourcesMethod": "rsync",
      "variables": [
        {
          "name": "BUILD_SAMPLES",
          "value": "True",
          "type": "BOOL"
        },
        {
          "name": "BUILD_TESTS",
          "value": "True",
          "type": "BOOL"
        },
        {
          "name": "BUILD_BENCHMARKS",
          "value": "True",
          "type": "BOOL"
        },
        {
          "name": "BUILD_RAPIDJSON_ARCHIVE",
          "value": "True",
          "type": "BOOL"
        },
        {
          "name": "BUILD_PUGIXML_ARCHIVE",
          "value": "True",
          "type": "BOOL"
        },
        {
          "name": "BUILD_RAPIDYAML_ARCHIVE",
          "value": "True",
          "type": "BOOL"
        },
        {
          "name": "BUILD_CSV_ARCHIVE",
          "value": "True",
          "type": "BOOL"
        },
        {
          "name": "BUILD_MSGPACK_ARCHIVE",
          "value": "True",
          "type": "BOOL"
        }
      ]
    },
    {
      "name": "Arm32-Linux-Debug",
      "generator": "Ninja",
      "configurationType": "Debug",
      "cmakeExecutable": "cmake",
      "remoteCopySourcesExclusionList": [ ".vs", ".git", "out", "bin" ],
      "cmakeCommandArgs": "-DCMAKE_TOOLCHAIN_FILE=/home/pavel/vcpkg/scripts/buildsystems/vcpkg.cmake -DVCPKG_TARGET_TRIPLET=bitserializer-arm32-linux -DVCPKG_CHAINLOAD_TOOLCHAIN_FILE=${remoteCMakeListsRoot}/cmake/toolchains/arm32-linux-toolchain.cmake",
      "buildCommandArgs": "",
      "ctestCommandArgs": "",
      "inheritEnvironments": [ "linux_arm" ],
      "remoteMachineName": "${defaultRemoteMachineName}",
      "remoteCMakeListsRoot": "$HOME/.vs/${projectDirName}/${workspaceHash}/src",
      "remoteBuildRoot": "$HOME/.vs/${projectDirName}/${workspaceHash}/out/build/${name}",
      "remoteInstallRoot": "$HOME/.vs/${projectDirName}/${workspaceHash}/out/install/${name}",
      "remoteCopySources": true,
      "rsyncCommandArgs": "-t --delete",
      "remoteCopyBuildOutput": false,
      "remoteCopySourcesMethod": "rsync",
      "variables": [
        {
          "name": "BUILD_SAMPLES",
          "value": "True",
          "type": "BOOL"
        },
        {
          "name": "BUILD_TESTS",
          "value": "True",
          "type": "BOOL"
        },
        {
          "name": "BUILD_BENCHMARKS",
          "value": "True",
          "type": "BOOL"
        },
        {
          "name": "BUILD_RAPIDJSON_ARCHIVE",
          "value": "True",
          "type": "BOOL"
        },
        {
          "name": "BUILD_PUGIXML_ARCHIVE",
          "value": "True",
          "type": "BOOL"
        },
        {
          "name": "BUILD_RAPIDYAML_ARCHIVE",
          "value": "True",
          "type": "BOOL"
        },
        {
          "name": "BUILD_CSV_ARCHIVE",
          "value": "True",
          "type": "BOOL"
        },
        {
          "name": "BUILD_MSGPACK_ARCHIVE",
          "value": "True",
          "type": "BOOL"
        }
      ]
    },
    {
      "name": "Arm32-Linux-Release",
      "generator": "Ninja",
      "configurationType": "RelWithDebInfo",
      "cmakeExecutable": "cmake",
      "remoteCopySourcesExclusionList": [ ".vs", ".git", "out", "bin" ],
      "cmakeCommandArgs": "-DCMAKE_TOOLCHAIN_FILE=/home/pavel/vcpkg/scripts/buildsystems/vcpkg.cmake -DVCPKG_TARGET_TRIPLET=bitserializer-arm32-linux -DVCPKG_CHAINLOAD_TOOLCHAIN_FILE=${remoteCMakeListsRoot}/cmake/toolchains/arm32-linux-toolchain.cmake",
      "buildCommandArgs": "",
      "ctestCommandArgs": "",
      "inheritEnvironments": [ "linux_arm" ],
      "remoteMachineName": "${defaultRemoteMachineName}",
      "remoteCMakeListsRoot": "$HOME/.vs/${projectDirName}/${workspaceHash}/src",
      "remoteBuildRoot": "$HOME/.vs/${projectDirName}/${workspaceHash}/out/build/${name}",
      "remoteInstallRoot": "$HOME/.vs/${projectDirName}/${workspaceHash}/out/install/${name}",
      "remoteCopySources": true,
      "rsyncCommandArgs": "-t --delete",
      "remoteCopyBuildOutput": false,
      "remoteCopySourcesMethod": "rsync",
      "variables": [
        {
          "name": "BUILD_SAMPLES",
          "value": "True",
          "type": "BOOL"
        },
        {
          "name": "BUILD_TESTS",
          "value": "True",
          "type": "BOOL"
        },
        {
          "name": "BUILD_BENCHMARKS",
          "value": "True",
          "type": "BOOL"
        },
        {
          "name": "BUILD_RAPIDJSON_ARCHIVE",
          "value": "True",
          "type": "BOOL"
        },
        {
          "name": "BUILD_PUGIXML_ARCHIVE",
          "value": "True",
          "type": "BOOL"
        },
        {
          "name": "BUILD_RAPIDYAML_ARCHIVE",
          "value": "True",
          "type": "BOOL"
        },
        {
          "name": "BUILD_CSV_ARCHIVE",
          "value": "True",
          "type": "BOOL"
        },
        {
          "name": "BUILD_MSGPACK_ARCHIVE",
          "value": "True",
          "type": "BOOL"
        }
      ]
    },
    {
      "name": "Arm64-Linux-CXX20-Debug",
      "generator": "Ninja",
      "configurationType": "Debug",
      "cmakeExecutable": "cmake",
      "remoteCopySourcesExclusionList": [ ".vs", ".git", "out", "bin" ],
      "cmakeCommandArgs": "-DCMAKE_TOOLCHAIN_FILE=/home/pavel/vcpkg/scripts/buildsystems/vcpkg.cmake -DVCPKG_TARGET_TRIPLET=bitserializer-arm64-linux -DVCPKG_CHAINLOAD_TOOLCHAIN_FILE=${remoteCMakeListsRoot}/cmake/toolchains/arm64-linux-toolchain.cmake -DCMAKE_CXX_STANDARD=20",
      "buildCommandArgs": "",
      "ctestCommandArgs": "",
      "inheritEnvironments": [ "linux_arm" ],
      "remoteMachineName": "${defaultRemoteMachineName}",
      "remoteCMakeListsRoot": "$HOME/.vs/${projectDirName}/${workspaceHash}/src",
      "remoteBuildRoot": "$HOME/.vs/${projectDirName}/${workspaceHash}/out/build/${name}",
      "remoteInstallRoot": "$HOME/.vs/${projectDirName}/${workspaceHash}/out/install/${name}",
      "remoteCopySources": true,
      "rsyncCommandArgs": "-t --delete",
      "remoteCopyBuildOutput": false,
      "remoteCopySourcesMethod": "rsync",
      "variables": [
        {
          "name": "BUILD_SAMPLES",
          "value": "True",
          "type": "BOOL"
        },
        {
          "name": "BUILD_TESTS",
          "value": "True",
          "type": "BOOL"
        },
        {
          "name": "BUILD_BENCHMARKS",
          "value": "True",
          "type": "BOOL"
        },
        {
          "name": "BUILD_RAPIDJSON_ARCHIVE",
          "value": "True",
          "type": "BOOL"
        },
        {
          "name": "BUILD_PUGIXML_ARCHIVE",
          "value": "True",
          "type": "BOOL"
        },
        {
          "name": "BUILD_RAPIDYAML_ARCHIVE",
          "value": "True",
          "type": "BOOL"
        },
        {
          "name": "BUILD_CSV_ARCHIVE",
          "value": "True",
          "type": "BOOL"
        },
        {
          "name": "BUILD_MSGPACK_ARCHIVE",
          "value": "True",
          "type": "BOOL"
        }
      ]
    },
    {
      "name": "Arm64-Linux-CXX20-Release",
      "generator": "Ninja",
      "configurationType": "RelWithDebInfo",
      "cmakeExecutable": "cmake",
      "remoteCopySourcesExclusionList": [ ".vs", ".git", "out", "bin" ],
      "cmakeCommandArgs": "-DCMAKE_TOOLCHAIN_FILE=/home/pavel/vcpkg/scripts/buildsystems/vcpkg.cmake -DVCPKG_TARGET_TRIPLET=bitserializer-arm64-linux -DVCPKG_CHAINLOAD_TOOLCHAIN_FILE=${remoteCMakeListsRoot}/cmake/toolchains/arm64-linux-toolchain.cmake -DCMAKE_CXX_STANDARD=20",
      "buildCommandArgs": "",
      "ctestCommandArgs": "",
      "inheritEnvironments": [ "linux_arm" ],
      "remoteMachineName": "${defaultRemoteMachineName}",
      "remoteCMakeListsRoot": "$HOME/.vs/${projectDirName}/${workspaceHash}/src",
      "remoteBuildRoot": "$HOME/.vs/${projectDirName}/${workspaceHash}/out/build/${name}",
      "remoteInstallRoot": "$HOME/.vs/${projectDirName}/${workspaceHash}/out/install/${name}",
      "remoteCopySources": true,
      "rsyncCommandArgs": "-t --delete",
      "remoteCopyBuildOutput": false,
      "remoteCopySourcesMethod": "rsync",
      "variables": [
        {
          "name": "BUILD_SAMPLES",
          "value": "True",
          "type": "BOOL"
        },
        {
          "name": "BUILD_TESTS",
          "value": "True",
          "type": "BOOL"
        },
        {
          "name": "BUILD_BENCHMARKS",
          "value": "True",
          "type": "BOOL"
        },
        {
          "name": "BUILD_RAPIDJSON_ARCHIVE",
          "value": "True",
          "type": "BOOL"
        },
        {
          "name": "BUILD_PUGIXML_ARCHIVE",
          "value": "True",
          "type": "BOOL"
        },
        {
          "name": "BUILD_RAPIDYAML_ARCHIVE",
          "value": "True",
          "type": "BOOL"
        },
        {
          "name": "BUILD_CSV_ARCHIVE",
          "value": "True",
          "type": "BOOL"
        },
        {
          "name": "BUILD_MSGPACK_ARCHIVE",
          "value": "True",
          "type": "BOOL"
        }
      ]
    },
    {
      "name": "Arm64be-Linux-Debug",
      "generator": "Ninja",
      "configurationType": "Debug",
      "cmakeExecutable": "cmake",
      "remoteCopySourcesExclusionList": [ ".vs", ".git", "out", "bin" ],
      "cmakeCommandArgs": "-DCMAKE_TOOLCHAIN_FILE=/home/pavel/vcpkg/scripts/buildsystems/vcpkg.cmake -DVCPKG_TARGET_TRIPLET=bitserializer-arm64be-linux -DVCPKG_CHAINLOAD_TOOLCHAIN_FILE=${remoteCMakeListsRoot}/cmake/toolchains/arm64be-linux-toolchain.cmake",
      "buildCommandArgs": "",
      "ctestCommandArgs": "",
      "inheritEnvironments": [ "linux_arm" ],
      "remoteMachineName": "${defaultRemoteMachineName}",
      "remoteCMakeListsRoot": "$HOME/.vs/${projectDirName}/${workspaceHash}/src",
      "remoteBuildRoot": "$HOME/.vs/${projectDirName}/${workspaceHash}/out/build/${name}",
      "remoteInstallRoot": "$HOME/.vs/${projectDirName}/${workspaceHash}/out/install/${name}",
      "remoteCopySources": true,
      "rsyncCommandArgs": "-t --delete",
      "remoteCopyBuildOutput": false,
      "remoteCopySourcesMethod": "rsync",
      "variables": [
        {
          "name": "BUILD_SAMPLES",
          "value": "True",
          "type": "BOOL"
        },
        {
          "name": "BUILD_TESTS",
          "value": "True",
          "type": "BOOL"
        },
        {
          "name": "BUILD_BENCHMARKS",
          "value": "True",
          "type": "BOOL"
        },
        {
          "name": "BUILD_RAPIDJSON_ARCHIVE",
          "value": "True",
          "type": "BOOL"
        },
        {
          "name": "BUILD_PUGIXML_ARCHIVE",
          "value": "True",
          "type": "BOOL"
        },
        {
          "name": "BUILD_RAPIDYAML_ARCHIVE",
          "value": "True",
          "type": "BOOL"
        },
        {
          "name": "BUILD_CSV_ARCHIVE",
          "value": "True",
          "type": "BOOL"
        },
        {
          "name": "BUILD_MSGPACK_ARCHIVE",
          "value": "True",
          "type": "BOOL"
        }
      ]
    },
    {
      "name": "Arm64be-Linux-Release",
      "generator": "Ninja",
      "configurationType": "RelWithDebInfo",
      "cmakeExecutable": "cmake",
      "remoteCopySourcesExclusionList": [ ".vs", ".git", "out", "bin" ],
      "cmakeCommandArgs": "-DCMAKE_TOOLCHAIN_FILE=/home/pavel/vcpkg/scripts/buildsystems/vcpkg.cmake -DVCPKG_TARGET_TRIPLET=bitserializer-arm64be-linux -DVCPKG_CHAINLOAD_TOOLCHAIN_FILE=${remoteCMakeListsRoot}/cmake/toolchains/arm64be-linux-toolchain.cmake",
      "buildCommandArgs": "",
      "ctestCommandArgs": "",
      "inheritEnvironments": [ "linux_arm" ],
      "remoteMachineName": "${defaultRemoteMachineName}",
      "remoteCMakeListsRoot": "$HOME/.vs/${projectDirName}/${workspaceHash}/src",
      "remoteBuildRoot": "$HOME/.vs/${projectDirName}/${workspaceHash}/out/build/${name}",
      "remoteInstallRoot": "$HOME/.vs/${projectDirName}/${workspaceHash}/out/install/${name}",
      "remoteCopySources": true,
      "rsyncCommandArgs": "-t --delete",
      "remoteCopyBuildOutput": false,
      "remoteCopySourcesMethod": "rsync",
      "variables": [
        {
          "name": "BUILD_SAMPLES",
          "value": "True",
          "type": "BOOL"
        },
        {
          "name": "BUILD_TESTS",
          "value": "True",
          "type": "BOOL"
        },
        {
          "name": "BUILD_BENCHMARKS",
          "value": "True",
          "type": "BOOL"
        },
        {
          "name": "BUILD_RAPIDJSON_ARCHIVE",
          "value": "True",
          "type": "BOOL"
        },
        {
          "name": "BUILD_PUGIXML_ARCHIVE",
          "value": "True",
          "type": "BOOL"
        },
        {
          "name": "BUILD_RAPIDYAML_ARCHIVE",
          "value": "True",
          "type": "BOOL"
        },
        {
          "name": "BUILD_CSV_ARCHIVE",
          "value": "True",
          "type": "BOOL"
        },
        {
          "name": "BUILD_MSGPACK_ARCHIVE",
          "value": "True",
          "type": "BOOL"
        }
      ]
    }
  ]
}